homoglyphs_fork/__init__.py
homoglyphs_fork/categories.json
homoglyphs_fork/confusables.json
homoglyphs_fork/core.py
homoglyphs_fork/languages.json
homoglyphs_fork-2.1.1.dist-info/WHEEL
homoglyphs_fork-2.1.1.dist-info/METADATA
homoglyphs_fork-2.1.1.dist-info/RECORD
