Metadata-Version: 2.3
Name: homoglyphs_fork
Version: 2.1.1
Summary: Homoglyphs
Author-email: orsinium <master_fess@mail.ru>
Maintainer-email: Matt Copperwaite <matt@copperwaite.net>
Classifier: Development Status :: 5 - Production/Stable
Classifier: Intended Audience :: Developers
Classifier: License :: OSI Approved :: MIT License
Classifier: Programming Language :: Python :: 3.9
Classifier: Programming Language :: Python :: 3.10
Classifier: Programming Language :: Python :: 3.11
Classifier: Programming Language :: Python :: 3.12
Classifier: Programming Language :: Python :: 3.13
Classifier: Programming Language :: Python :: 3
Classifier: Programming Language :: Python
Classifier: Topic :: Software Development :: Libraries :: Python Modules
Project-URL: Home, https://github.com/yamatt/homoglyphs
